{
  "version": "5",
  "dialect": "pg",
  "entries": [
    {
      "idx": 0,
      "version": "5",
      "when": 1710486320195,
      "tag": "0000_woozy_jasper_sitwell",
      "breakpoints": true
    },
    {
      "idx": 1,
      "version": "5",
      "when": 1710567031299,
      "tag": "0001_amused_wither",
      "breakpoints": true
    },
    {
      "idx": 2,
      "version": "5",
      "when": 1710625591523,
      "tag": "0002_blue_matthew_murdock",
      "breakpoints": true
    },
    {
      "idx": 3,
      "version": "5",
      "when": 1710695046403,
      "tag": "0003_whole_post",
      "breakpoints": true
    },
    {
      "idx": 4,
      "version": "5",
      "when": 1710909289190,
      "tag": "0004_yummy_monster_badoon",
      "breakpoints": true
    },
    {
      "idx": 5,
      "version": "5",
      "when": 1710982945826,
      "tag": "0005_yummy_boom_boom",
      "breakpoints": true
    },
    {
      "idx": 8,
      "version": "5",
      "when": 1710984708200,
      "tag": "0008_mysterious_iceman",
      "breakpoints": true
    },
    {
      "idx": 9,
      "version": "5",
      "when": 1711070760278,
      "tag": "0009_superb_jocasta",
      "breakpoints": true
    },
    {
      "idx": 10,
      "version": "5",
      "when": 1711074455236,
      "tag": "0010_boring_punisher",
      "breakpoints": true
    },
    {
      "idx": 11,
      "version": "5",
      "when": 1711076159011,
      "tag": "0011_watery_sister_grimm",
      "breakpoints": true
    },
    {
      "idx": 12,
      "version": "5",
      "when": 1711151902382,
      "tag": "0012_glamorous_mathemanic",
      "breakpoints": true
    },
    {
      "idx": 14,
      "version": "5",
      "when": 1711211527973,
      "tag": "0014_tan_mathemanic",
      "breakpoints": true
    },
    {
      "idx": 15,
      "version": "5",
      "when": 1711211609686,
      "tag": "0015_sparkling_kat_farrell",
      "breakpoints": true
    },
    {
      "idx": 16,
      "version": "5",
      "when": 1711595606536,
      "tag": "0016_lazy_the_phantom",
      "breakpoints": true
    },
    {
      "idx": 17,
      "version": "5",
      "when": 1711731959912,
      "tag": "0017_zippy_sebastian_shaw",
      "breakpoints": true
    },
    {
      "idx": 18,
      "version": "5",
      "when": 1711735192017,
      "tag": "0018_aspiring_thunderbolt_ross",
      "breakpoints": true
    },
    {
      "idx": 19,
      "version": "5",
      "when": 1711913772406,
      "tag": "0019_medical_monster_badoon",
      "breakpoints": true
    },
    {
      "idx": 21,
      "version": "5",
      "when": 1711921215208,
      "tag": "0021_old_hex",
      "breakpoints": true
    },
    {
      "idx": 22,
      "version": "5",
      "when": 1711930562524,
      "tag": "0022_supreme_major_mapleleaf",
      "breakpoints": true
    },
    {
      "idx": 23,
      "version": "5",
      "when": 1711930631720,
      "tag": "0023_petite_hedge_knight",
      "breakpoints": true
    },
    {
      "idx": 24,
      "version": "5",
      "when": 1711931040316,
      "tag": "0024_gray_virginia_dare",
      "breakpoints": true
    },
    {
      "idx": 25,
      "version": "5",
      "when": 1711931069626,
      "tag": "0025_lazy_george_stacy",
      "breakpoints": true
    },
    {
      "idx": 26,
      "version": "5",
      "when": 1711931115379,
      "tag": "0026_burly_whistler",
      "breakpoints": true
    },
    {
      "idx": 27,
      "version": "5",
      "when": 1712013580725,
      "tag": "0027_typical_husk",
      "breakpoints": true
    },
    {
      "idx": 28,
      "version": "5",
      "when": 1712013844187,
      "tag": "0028_minor_veda",
      "breakpoints": true
    }
  ]
}